skf/__init__.py
skf-0.0.2.dist-info/METADATA
skf-0.0.2.dist-info/WHEEL
skf-0.0.2.dist-info/top_level.txt
skf-0.0.2.dist-info/RECORD
